{
  "checkbox-card/detailed": {
    "title": "Detailed"
  },
  "checkbox-card/form": {
    "title": "Form"
  },
  "checkbox-card/grid": {
    "title": "Grid"
  },
  "checkbox-card/indented": {
    "title": "Indented"
  },
  "checkbox-card/leading-images": {
    "title": "Leading Images"
  },
  "checkbox-card": {
    "title": "Checkbox Card"
  },
  "checkbox-card/round": {
    "title": "Round"
  },
  "checkbox-card/top-images": {
    "title": "Top Images"
  },
  "checkbox-card/trailing-images": {
    "title": "Trailing Images"
  },
  "combobox-group/custom-items": {
    "title": "Custom Items"
  },
  "combobox-group": {
    "title": "Combobox Group"
  },
  "combobox-group/sticky-group-labels": {
    "title": "Sticky Group Labels"
  },
  "dialog-framer-motion": {
    "title": "Dialog with Motion"
  },
  "disclosure-react-aria/checklist": {
    "title": "Checklist"
  },
  "disclosure-react-aria/description": {
    "title": "Visible Description"
  },
  "disclosure-react-aria/group": {
    "title": "Group"
  },
  "disclosure-react-aria/icon-description": {
    "title": "Icon and Description"
  },
  "disclosure-react-aria/icon": {
    "title": "Icon"
  },
  "disclosure-react-aria/nested": {
    "title": "Nested"
  },
  "disclosure-react-aria": {
    "title": "Basic Example"
  },
  "disclosure/_component": {
    "title": "Disclosure"
  },
  "disclosure/actions": {
    "title": "Actions"
  },
  "disclosure/checklist": {
    "title": "Checklist"
  },
  "disclosure/description": {
    "title": "Visible Description"
  },
  "disclosure/group": {
    "title": "Group"
  },
  "disclosure/icon-description": {
    "title": "Icon and Description"
  },
  "disclosure/icon": {
    "title": "Icon"
  },
  "disclosure/navigation": {
    "title": "Navigation",
    "fullscreen": true
  },
  "disclosure/nested": {
    "title": "Nested"
  },
  "disclosure": {
    "title": "Basic Example"
  },
  "popover/_component": {
    "title": "Popover"
  },
  "separator/_component": {
    "title": "Separator"
  },
  "aria-labelledby-aria-label": {
    "title": "aria-labelledby-aria-label"
  },
  "ariakit-tailwind": {
    "title": "Ariakit Tailwind"
  },
  "button-form-status-4540": {
    "title": "Button with form status"
  },
  "combobox-5165": {
    "title": "combobox-5165"
  },
  "combobox-5518": {
    "title": "combobox-5518"
  },
  "composite-menu-3768": {
    "title": "composite-menu-3768"
  },
  "counter-nextjs": {
    "title": "Counter Next.js",
    "source": "sandbox",
    "frameworks": ["react"]
  },
  "dialog-3403": {
    "title": "dialog-3403"
  },
  "dialog-5057": {
    "title": "dialog-5057"
  },
  "dialog-5156": {
    "title": "dialog-5156"
  },
  "dialog-combobox-4825": {
    "title": "dialog-combobox-4825"
  },
  "dialog-disclosure-5224": {
    "title": "dialog-disclosure-5224"
  },
  "disclosure-content-transition-lifecycle": {
    "title": "Disclosure content transition lifecycle"
  },
  "focus-trap-region": {
    "title": "Focus trap region"
  },
  "focusable-click-focus": {
    "title": "Focusable click focus"
  },
  "form-3607": {
    "title": "form-3607"
  },
  "form-radio-3833": {
    "title": "form-radio-3833"
  },
  "heading-level-computation": {
    "title": "heading-level-computation"
  },
  "hovercard-5156": {
    "title": "hovercard-5156"
  },
  "hovercard-nested-listener": {
    "title": "Hovercard nested listener"
  },
  "menu-3214": {
    "title": "Multiple menus update depth"
  },
  "menu-4291": {
    "title": "Menu persistent disclosure focus"
  },
  "menu-4904": {
    "title": "Menu in popup window"
  },
  "menu-4938": {
    "title": "menu-4938"
  },
  "menu-5899": {
    "title": "Menu auto focus on show"
  },
  "menu-button-4133": {
    "title": "menu-button-4133"
  },
  "menu-dialog-close": {
    "title": "Menu dialog close"
  },
  "menu-nested-combobox-4443": {
    "title": "menu-nested-combobox-4443"
  },
  "menu-nested-combobox-hide": {
    "title": "menu-nested-combobox-hide"
  },
  "radio-group-3833": {
    "title": "radio-group-3833"
  },
  "select-4593": {
    "title": "select-4593"
  },
  "select-combobox-3837": {
    "title": "select-combobox-3837"
  },
  "select-combobox-5047": {
    "title": "select-combobox-5047"
  },
  "select-combobox-form-3323": {
    "title": "select-combobox-form-3323"
  },
  "select-item-5691": {
    "title": "select-item-5691"
  },
  "tab-4213": {
    "title": "tab-4213"
  },
  "tab-form-5273": {
    "title": "tab-form-5273"
  },
  "tab-panel-5692": {
    "title": "tab-panel-5692"
  },
  "tooltip-4894": {
    "title": "tooltip-4894"
  },
  "tooltip-865": {
    "title": "tooltip-865"
  },
  "tooltip-cross-anchor": {
    "title": "tooltip-cross-anchor"
  }
}
